{
    "suppliers": [
        {
            "supplier_id": 1,
            "supplier_name": "supplier01",
            "supplier_phone": "0888888888",
            "supplier_iban": "CY 17 002 00128 0000001200527600",
            "supplier_status": "Active"
        },
        {
            "supplier_id": 2,
            "supplier_name": "supplier03",
            "supplier_phone": "0888888883",
            "supplier_iban": "CZ 17 002 00128 0000001200527600",
            "supplier_status": "Active"
        }
    ]
}